{
  "version": "5",
  "dialect": "mysql",
  "id": "e9f340d0-b47a-45f3-abe3-474dca404b26",
  "prevId": "b33dc5d7-76d4-40d7-a726-078ed72e137a",
  "tables": {
    "daily_performance": {
      "name": "daily_performance",
      "columns": {
        "id": {
          "name": "id",
          "type": "int",
          "primaryKey": false,
          "notNull": true,
          "autoincrement": true
        },
        "userId": {
          "name": "userId",
          "type": "int",
          "primaryKey": false,
          "notNull": true,
          "autoincrement": false
        },
        "date": {
          "name": "date",
          "type": "varchar(10)",
          "primaryKey": false,
          "notNull": true,
          "autoincrement": false
        },
        "totalPnl": {
          "name": "totalPnl",
          "type": "decimal(10,2)",
          "primaryKey": false,
          "notNull": true,
          "autoincrement": false,
          "default": "'0'"
        },
        "totalPnlPoints": {
          "name": "totalPnlPoints",
          "type": "decimal(10,2)",
          "primaryKey": false,
          "notNull": true,
          "autoincrement": false,
          "default": "'0'"
        },
        "tradesCount": {
          "name": "tradesCount",
          "type": "int",
          "primaryKey": false,
          "notNull": true,
          "autoincrement": false,
          "default": 0
        },
        "winsCount": {
          "name": "winsCount",
          "type": "int",
          "primaryKey": false,
          "notNull": true,
          "autoincrement": false,
          "default": 0
        },
        "lossesCount": {
          "name": "lossesCount",
          "type": "int",
          "primaryKey": false,
          "notNull": true,
          "autoincrement": false,
          "default": 0
        },
        "maxDrawdown": {
          "name": "maxDrawdown",
          "type": "decimal(10,2)",
          "primaryKey": false,
          "notNull": true,
          "autoincrement": false,
          "default": "'0'"
        },
        "createdAt": {
          "name": "createdAt",
          "type": "timestamp",
          "primaryKey": false,
          "notNull": true,
          "autoincrement": false,
          "default": "(now())"
        },
        "updatedAt": {
          "name": "updatedAt",
          "type": "timestamp",
          "primaryKey": false,
          "notNull": true,
          "autoincrement": false,
          "onUpdate": true,
          "default": "(now())"
        }
      },
      "indexes": {},
      "foreignKeys": {},
      "compositePrimaryKeys": {
        "daily_performance_id": {
          "name": "daily_performance_id",
          "columns": [
            "id"
          ]
        }
      },
      "uniqueConstraints": {},
      "checkConstraint": {}
    },
    "educational_content": {
      "name": "educational_content",
      "columns": {
        "id": {
          "name": "id",
          "type": "int",
          "primaryKey": false,
          "notNull": true,
          "autoincrement": true
        },
        "topic": {
          "name": "topic",
          "type": "varchar(100)",
          "primaryKey": false,
          "notNull": true,
          "autoincrement": false
        },
        "content": {
          "name": "content",
          "type": "text",
          "primaryKey": false,
          "notNull": true,
          "autoincrement": false
        },
        "updatedAt": {
          "name": "updatedAt",
          "type": "timestamp",
          "primaryKey": false,
          "notNull": true,
          "autoincrement": false,
          "onUpdate": true,
          "default": "(now())"
        }
      },
      "indexes": {},
      "foreignKeys": {},
      "compositePrimaryKeys": {
        "educational_content_id": {
          "name": "educational_content_id",
          "columns": [
            "id"
          ]
        }
      },
      "uniqueConstraints": {
        "educational_content_topic_unique": {
          "name": "educational_content_topic_unique",
          "columns": [
            "topic"
          ]
        }
      },
      "checkConstraint": {}
    },
    "inter_credentials": {
      "name": "inter_credentials",
      "columns": {
        "id": {
          "name": "id",
          "type": "int",
          "primaryKey": false,
          "notNull": true,
          "autoincrement": true
        },
        "userId": {
          "name": "userId",
          "type": "int",
          "primaryKey": false,
          "notNull": true,
          "autoincrement": false
        },
        "clientId": {
          "name": "clientId",
          "type": "varchar(255)",
          "primaryKey": false,
          "notNull": false,
          "autoincrement": false
        },
        "clientSecretHash": {
          "name": "clientSecretHash",
          "type": "varchar(255)",
          "primaryKey": false,
          "notNull": false,
          "autoincrement": false
        },
        "certFingerprint": {
          "name": "certFingerprint",
          "type": "varchar(255)",
          "primaryKey": false,
          "notNull": false,
          "autoincrement": false
        },
        "accountNumber": {
          "name": "accountNumber",
          "type": "varchar(50)",
          "primaryKey": false,
          "notNull": false,
          "autoincrement": false
        },
        "environment": {
          "name": "environment",
          "type": "enum('sandbox','production')",
          "primaryKey": false,
          "notNull": true,
          "autoincrement": false,
          "default": "'sandbox'"
        },
        "status": {
          "name": "status",
          "type": "enum('not_configured','pending','active','error')",
          "primaryKey": false,
          "notNull": true,
          "autoincrement": false,
          "default": "'not_configured'"
        },
        "lastTestedAt": {
          "name": "lastTestedAt",
          "type": "timestamp",
          "primaryKey": false,
          "notNull": false,
          "autoincrement": false
        },
        "lastError": {
          "name": "lastError",
          "type": "text",
          "primaryKey": false,
          "notNull": false,
          "autoincrement": false
        },
        "createdAt": {
          "name": "createdAt",
          "type": "timestamp",
          "primaryKey": false,
          "notNull": true,
          "autoincrement": false,
          "default": "(now())"
        },
        "updatedAt": {
          "name": "updatedAt",
          "type": "timestamp",
          "primaryKey": false,
          "notNull": true,
          "autoincrement": false,
          "onUpdate": true,
          "default": "(now())"
        }
      },
      "indexes": {},
      "foreignKeys": {},
      "compositePrimaryKeys": {
        "inter_credentials_id": {
          "name": "inter_credentials_id",
          "columns": [
            "id"
          ]
        }
      },
      "uniqueConstraints": {
        "inter_credentials_userId_unique": {
          "name": "inter_credentials_userId_unique",
          "columns": [
            "userId"
          ]
        }
      },
      "checkConstraint": {}
    },
    "oco_configs": {
      "name": "oco_configs",
      "columns": {
        "id": {
          "name": "id",
          "type": "int",
          "primaryKey": false,
          "notNull": true,
          "autoincrement": true
        },
        "userId": {
          "name": "userId",
          "type": "int",
          "primaryKey": false,
          "notNull": true,
          "autoincrement": false
        },
        "name": {
          "name": "name",
          "type": "varchar(100)",
          "primaryKey": false,
          "notNull": true,
          "autoincrement": false
        },
        "stopLossPoints": {
          "name": "stopLossPoints",
          "type": "int",
          "primaryKey": false,
          "notNull": true,
          "autoincrement": false,
          "default": 150
        },
        "takeProfitPoints": {
          "name": "takeProfitPoints",
          "type": "int",
          "primaryKey": false,
          "notNull": true,
          "autoincrement": false,
          "default": 250
        },
        "breakevenTriggerPoints": {
          "name": "breakevenTriggerPoints",
          "type": "int",
          "primaryKey": false,
          "notNull": true,
          "autoincrement": false,
          "default": 100
        },
        "trailingStopPoints": {
          "name": "trailingStopPoints",
          "type": "int",
          "primaryKey": false,
          "notNull": true,
          "autoincrement": false,
          "default": 50
        },
        "trailingStopTriggerPoints": {
          "name": "trailingStopTriggerPoints",
          "type": "int",
          "primaryKey": false,
          "notNull": true,
          "autoincrement": false,
          "default": 150
        },
        "defaultContracts": {
          "name": "defaultContracts",
          "type": "int",
          "primaryKey": false,
          "notNull": true,
          "autoincrement": false,
          "default": 5
        },
        "isActive": {
          "name": "isActive",
          "type": "boolean",
          "primaryKey": false,
          "notNull": true,
          "autoincrement": false,
          "default": true
        },
        "createdAt": {
          "name": "createdAt",
          "type": "timestamp",
          "primaryKey": false,
          "notNull": true,
          "autoincrement": false,
          "default": "(now())"
        },
        "updatedAt": {
          "name": "updatedAt",
          "type": "timestamp",
          "primaryKey": false,
          "notNull": true,
          "autoincrement": false,
          "onUpdate": true,
          "default": "(now())"
        }
      },
      "indexes": {},
      "foreignKeys": {},
      "compositePrimaryKeys": {
        "oco_configs_id": {
          "name": "oco_configs_id",
          "columns": [
            "id"
          ]
        }
      },
      "uniqueConstraints": {},
      "checkConstraint": {}
    },
    "predictions": {
      "name": "predictions",
      "columns": {
        "id": {
          "name": "id",
          "type": "int",
          "primaryKey": false,
          "notNull": true,
          "autoincrement": true
        },
        "userId": {
          "name": "userId",
          "type": "int",
          "primaryKey": false,
          "notNull": true,
          "autoincrement": false
        },
        "symbol": {
          "name": "symbol",
          "type": "varchar(20)",
          "primaryKey": false,
          "notNull": true,
          "autoincrement": false,
          "default": "'WIN'"
        },
        "signalType": {
          "name": "signalType",
          "type": "enum('buy','sell','neutral','avoid')",
          "primaryKey": false,
          "notNull": true,
          "autoincrement": false
        },
        "confidence": {
          "name": "confidence",
          "type": "int",
          "primaryKey": false,
          "notNull": true,
          "autoincrement": false,
          "default": 50
        },
        "entryZoneLow": {
          "name": "entryZoneLow",
          "type": "decimal(10,2)",
          "primaryKey": false,
          "notNull": false,
          "autoincrement": false
        },
        "entryZoneHigh": {
          "name": "entryZoneHigh",
          "type": "decimal(10,2)",
          "primaryKey": false,
          "notNull": false,
          "autoincrement": false
        },
        "stopLoss": {
          "name": "stopLoss",
          "type": "decimal(10,2)",
          "primaryKey": false,
          "notNull": false,
          "autoincrement": false
        },
        "takeProfit": {
          "name": "takeProfit",
          "type": "decimal(10,2)",
          "primaryKey": false,
          "notNull": false,
          "autoincrement": false
        },
        "reasoning": {
          "name": "reasoning",
          "type": "text",
          "primaryKey": false,
          "notNull": false,
          "autoincrement": false
        },
        "marketContext": {
          "name": "marketContext",
          "type": "text",
          "primaryKey": false,
          "notNull": false,
          "autoincrement": false
        },
        "riskLevel": {
          "name": "riskLevel",
          "type": "enum('low','medium','high')",
          "primaryKey": false,
          "notNull": true,
          "autoincrement": false,
          "default": "'medium'"
        },
        "status": {
          "name": "status",
          "type": "enum('pending','executed','ignored','won','lost','expired')",
          "primaryKey": false,
          "notNull": true,
          "autoincrement": false,
          "default": "'pending'"
        },
        "expiresAt": {
          "name": "expiresAt",
          "type": "timestamp",
          "primaryKey": false,
          "notNull": false,
          "autoincrement": false
        },
        "createdAt": {
          "name": "createdAt",
          "type": "timestamp",
          "primaryKey": false,
          "notNull": true,
          "autoincrement": false,
          "default": "(now())"
        },
        "updatedAt": {
          "name": "updatedAt",
          "type": "timestamp",
          "primaryKey": false,
          "notNull": true,
          "autoincrement": false,
          "onUpdate": true,
          "default": "(now())"
        }
      },
      "indexes": {},
      "foreignKeys": {},
      "compositePrimaryKeys": {
        "predictions_id": {
          "name": "predictions_id",
          "columns": [
            "id"
          ]
        }
      },
      "uniqueConstraints": {},
      "checkConstraint": {}
    },
    "trades": {
      "name": "trades",
      "columns": {
        "id": {
          "name": "id",
          "type": "int",
          "primaryKey": false,
          "notNull": true,
          "autoincrement": true
        },
        "userId": {
          "name": "userId",
          "type": "int",
          "primaryKey": false,
          "notNull": true,
          "autoincrement": false
        },
        "symbol": {
          "name": "symbol",
          "type": "varchar(20)",
          "primaryKey": false,
          "notNull": true,
          "autoincrement": false,
          "default": "'WIN'"
        },
        "side": {
          "name": "side",
          "type": "enum('buy','sell')",
          "primaryKey": false,
          "notNull": true,
          "autoincrement": false
        },
        "contracts": {
          "name": "contracts",
          "type": "int",
          "primaryKey": false,
          "notNull": true,
          "autoincrement": false
        },
        "entryPrice": {
          "name": "entryPrice",
          "type": "decimal(10,2)",
          "primaryKey": false,
          "notNull": true,
          "autoincrement": false
        },
        "exitPrice": {
          "name": "exitPrice",
          "type": "decimal(10,2)",
          "primaryKey": false,
          "notNull": false,
          "autoincrement": false
        },
        "stopLoss": {
          "name": "stopLoss",
          "type": "decimal(10,2)",
          "primaryKey": false,
          "notNull": false,
          "autoincrement": false
        },
        "takeProfit": {
          "name": "takeProfit",
          "type": "decimal(10,2)",
          "primaryKey": false,
          "notNull": false,
          "autoincrement": false
        },
        "pnl": {
          "name": "pnl",
          "type": "decimal(10,2)",
          "primaryKey": false,
          "notNull": false,
          "autoincrement": false
        },
        "pnlPoints": {
          "name": "pnlPoints",
          "type": "decimal(10,2)",
          "primaryKey": false,
          "notNull": false,
          "autoincrement": false
        },
        "status": {
          "name": "status",
          "type": "enum('open','closed','stopped','target')",
          "primaryKey": false,
          "notNull": true,
          "autoincrement": false,
          "default": "'open'"
        },
        "notes": {
          "name": "notes",
          "type": "text",
          "primaryKey": false,
          "notNull": false,
          "autoincrement": false
        },
        "entryAt": {
          "name": "entryAt",
          "type": "timestamp",
          "primaryKey": false,
          "notNull": true,
          "autoincrement": false,
          "default": "(now())"
        },
        "exitAt": {
          "name": "exitAt",
          "type": "timestamp",
          "primaryKey": false,
          "notNull": false,
          "autoincrement": false
        },
        "createdAt": {
          "name": "createdAt",
          "type": "timestamp",
          "primaryKey": false,
          "notNull": true,
          "autoincrement": false,
          "default": "(now())"
        }
      },
      "indexes": {},
      "foreignKeys": {},
      "compositePrimaryKeys": {
        "trades_id": {
          "name": "trades_id",
          "columns": [
            "id"
          ]
        }
      },
      "uniqueConstraints": {},
      "checkConstraint": {}
    },
    "user_settings": {
      "name": "user_settings",
      "columns": {
        "id": {
          "name": "id",
          "type": "int",
          "primaryKey": false,
          "notNull": true,
          "autoincrement": true
        },
        "userId": {
          "name": "userId",
          "type": "int",
          "primaryKey": false,
          "notNull": true,
          "autoincrement": false
        },
        "preferredContracts": {
          "name": "preferredContracts",
          "type": "int",
          "primaryKey": false,
          "notNull": true,
          "autoincrement": false,
          "default": 5
        },
        "riskProfile": {
          "name": "riskProfile",
          "type": "enum('conservative','moderate','aggressive')",
          "primaryKey": false,
          "notNull": true,
          "autoincrement": false,
          "default": "'moderate'"
        },
        "dailyGoal": {
          "name": "dailyGoal",
          "type": "decimal(10,2)",
          "primaryKey": false,
          "notNull": true,
          "autoincrement": false,
          "default": "'2000'"
        },
        "dailyLimit": {
          "name": "dailyLimit",
          "type": "decimal(10,2)",
          "primaryKey": false,
          "notNull": true,
          "autoincrement": false,
          "default": "'1000'"
        },
        "stopLossPoints": {
          "name": "stopLossPoints",
          "type": "int",
          "primaryKey": false,
          "notNull": true,
          "autoincrement": false,
          "default": 150
        },
        "takeProfitPoints": {
          "name": "takeProfitPoints",
          "type": "int",
          "primaryKey": false,
          "notNull": true,
          "autoincrement": false,
          "default": 250
        },
        "enableAiPredictions": {
          "name": "enableAiPredictions",
          "type": "boolean",
          "primaryKey": false,
          "notNull": true,
          "autoincrement": false,
          "default": true
        },
        "enableSoundAlerts": {
          "name": "enableSoundAlerts",
          "type": "boolean",
          "primaryKey": false,
          "notNull": true,
          "autoincrement": false,
          "default": true
        },
        "enableAutoBreakeven": {
          "name": "enableAutoBreakeven",
          "type": "boolean",
          "primaryKey": false,
          "notNull": true,
          "autoincrement": false,
          "default": true
        },
        "pauseAfterLosses": {
          "name": "pauseAfterLosses",
          "type": "int",
          "primaryKey": false,
          "notNull": true,
          "autoincrement": false,
          "default": 3
        },
        "timezone": {
          "name": "timezone",
          "type": "varchar(50)",
          "primaryKey": false,
          "notNull": true,
          "autoincrement": false,
          "default": "'America/Sao_Paulo'"
        },
        "tradingPaused": {
          "name": "tradingPaused",
          "type": "boolean",
          "primaryKey": false,
          "notNull": true,
          "autoincrement": false,
          "default": false
        },
        "enableLiveTrading": {
          "name": "enableLiveTrading",
          "type": "boolean",
          "primaryKey": false,
          "notNull": true,
          "autoincrement": false,
          "default": false
        },
        "requireOrderConfirmation": {
          "name": "requireOrderConfirmation",
          "type": "boolean",
          "primaryKey": false,
          "notNull": true,
          "autoincrement": false,
          "default": true
        },
        "breakevenTriggerPoints": {
          "name": "breakevenTriggerPoints",
          "type": "int",
          "primaryKey": false,
          "notNull": true,
          "autoincrement": false,
          "default": 100
        },
        "maxContractsLimit": {
          "name": "maxContractsLimit",
          "type": "int",
          "primaryKey": false,
          "notNull": true,
          "autoincrement": false,
          "default": 10
        },
        "marginLimitBrl": {
          "name": "marginLimitBrl",
          "type": "decimal(10,2)",
          "primaryKey": false,
          "notNull": true,
          "autoincrement": false,
          "default": "'5000'"
        },
        "createdAt": {
          "name": "createdAt",
          "type": "timestamp",
          "primaryKey": false,
          "notNull": true,
          "autoincrement": false,
          "default": "(now())"
        },
        "updatedAt": {
          "name": "updatedAt",
          "type": "timestamp",
          "primaryKey": false,
          "notNull": true,
          "autoincrement": false,
          "onUpdate": true,
          "default": "(now())"
        }
      },
      "indexes": {},
      "foreignKeys": {},
      "compositePrimaryKeys": {
        "user_settings_id": {
          "name": "user_settings_id",
          "columns": [
            "id"
          ]
        }
      },
      "uniqueConstraints": {
        "user_settings_userId_unique": {
          "name": "user_settings_userId_unique",
          "columns": [
            "userId"
          ]
        }
      },
      "checkConstraint": {}
    },
    "users": {
      "name": "users",
      "columns": {
        "id": {
          "name": "id",
          "type": "int",
          "primaryKey": false,
          "notNull": true,
          "autoincrement": true
        },
        "openId": {
          "name": "openId",
          "type": "varchar(64)",
          "primaryKey": false,
          "notNull": true,
          "autoincrement": false
        },
        "name": {
          "name": "name",
          "type": "text",
          "primaryKey": false,
          "notNull": false,
          "autoincrement": false
        },
        "email": {
          "name": "email",
          "type": "varchar(320)",
          "primaryKey": false,
          "notNull": false,
          "autoincrement": false
        },
        "loginMethod": {
          "name": "loginMethod",
          "type": "varchar(64)",
          "primaryKey": false,
          "notNull": false,
          "autoincrement": false
        },
        "role": {
          "name": "role",
          "type": "enum('user','admin')",
          "primaryKey": false,
          "notNull": true,
          "autoincrement": false,
          "default": "'user'"
        },
        "createdAt": {
          "name": "createdAt",
          "type": "timestamp",
          "primaryKey": false,
          "notNull": true,
          "autoincrement": false,
          "default": "(now())"
        },
        "updatedAt": {
          "name": "updatedAt",
          "type": "timestamp",
          "primaryKey": false,
          "notNull": true,
          "autoincrement": false,
          "onUpdate": true,
          "default": "(now())"
        },
        "lastSignedIn": {
          "name": "lastSignedIn",
          "type": "timestamp",
          "primaryKey": false,
          "notNull": true,
          "autoincrement": false,
          "default": "(now())"
        },
        "passwordHash": {
          "name": "passwordHash",
          "type": "varchar(255)",
          "primaryKey": false,
          "notNull": false,
          "autoincrement": false
        }
      },
      "indexes": {},
      "foreignKeys": {},
      "compositePrimaryKeys": {
        "users_id": {
          "name": "users_id",
          "columns": [
            "id"
          ]
        }
      },
      "uniqueConstraints": {
        "users_openId_unique": {
          "name": "users_openId_unique",
          "columns": [
            "openId"
          ]
        }
      },
      "checkConstraint": {}
    }
  },
  "views": {},
  "_meta": {
    "schemas": {},
    "tables": {},
    "columns": {}
  },
  "internal": {
    "tables": {},
    "indexes": {}
  }
}